{
    "domain": "awsglobalaccelerator.com",
    "owner": {},
    "source": [
        "DuckDuckGo-GB"
    ],
    "prevalence": 0.000721,
    "sites": 7,
    "subdomains": [
        "ab50c11a81c4fa41b",
        "a0e88012cb437ad49"
    ],
    "cnames": [
        {
            "original": "analytics.ableton.com",
            "resolved": "ab50c11a81c4fa41b.awsglobalaccelerator.com"
        },
        {
            "original": "internal-api.monzo.com",
            "resolved": "a0e88012cb437ad49.awsglobalaccelerator.com"
        }
    ],
    "fingerprinting": 2,
    "resources": [
        {
            "rule": "awsglobalaccelerator\\.com\\/js\\/container_R5JVetMm\\.js",
            "cookies": 0.000206,
            "fingerprinting": 2,
            "subdomains": [
                "ab50c11a81c4fa41b"
            ],
            "apis": {},
            "sites": 2,
            "prevalence": 0.000206,
            "cnames": [
                {
                    "original": "analytics.ableton.com",
                    "resolved": "ab50c11a81c4fa41b.awsglobalaccelerator.com"
                }
            ],
            "responseHashes": [
                "b3d44e0760c3f6a84cda7c32f3f5943c60e2962c7ea78d37f2abe2d8d07c7876"
            ],
            "type": "Script",
            "firstPartyCookies": {},
            "firstPartyCookiesSent": {},
            "exampleSites": [
                "ableton.com",
                "www.ableton.com"
            ]
        },
        {
            "rule": "awsglobalaccelerator\\.com\\/static\\/util\\.js",
            "cookies": 0,
            "fingerprinting": 0,
            "subdomains": [
                "a0e88012cb437ad49"
            ],
            "apis": {},
            "sites": 2,
            "prevalence": 0.000206,
            "cnames": [
                {
                    "original": "internal-api.monzo.com",
                    "resolved": "a0e88012cb437ad49.awsglobalaccelerator.com"
                }
            ],
            "responseHashes": [],
            "type": "Script",
            "firstPartyCookies": {},
            "firstPartyCookiesSent": {},
            "exampleSites": [
                "monzo.com",
                "web.monzo.com"
            ]
        },
        {
            "rule": "awsglobalaccelerator\\.com\\/oauth2\\/token",
            "cookies": 0,
            "fingerprinting": 0,
            "subdomains": [
                "a0e88012cb437ad49"
            ],
            "apis": {},
            "sites": 2,
            "prevalence": 0.000206,
            "cnames": [
                {
                    "original": "internal-api.monzo.com",
                    "resolved": "a0e88012cb437ad49.awsglobalaccelerator.com"
                }
            ],
            "responseHashes": [
                "a5160185bfef9d1098b27a47e1963eb37c39ba63e7517e5f0914468783d406b9"
            ],
            "type": "Fetch",
            "firstPartyCookies": {},
            "firstPartyCookiesSent": {},
            "exampleSites": [
                "monzo.com",
                "web.monzo.com"
            ]
        },
        {
            "rule": "awsglobalaccelerator\\.com\\/static\\/monzo_framework\\.png",
            "cookies": 0,
            "fingerprinting": 0,
            "subdomains": [
                "a0e88012cb437ad49"
            ],
            "apis": {},
            "sites": 2,
            "prevalence": 0.000206,
            "cnames": [
                {
                    "original": "internal-api.monzo.com",
                    "resolved": "a0e88012cb437ad49.awsglobalaccelerator.com"
                }
            ],
            "responseHashes": [
                "968b17baf99ffc8097fdbe0d8552113c2f6e7da2a63e3967f24811e2e2e0a312"
            ],
            "type": "Image",
            "firstPartyCookies": {},
            "firstPartyCookiesSent": {},
            "exampleSites": [
                "monzo.com",
                "web.monzo.com"
            ]
        }
    ],
    "categories": [],
    "performance": {},
    "cookies": 0.000309,
    "topInitiators": [
        {
            "domain": "d4j85rjepgcta.cloudfront.net",
            "prevalence": 0.5
        },
        {
            "domain": "simpleonlinedoctor.com.au",
            "prevalence": 0.5
        }
    ],
    "types": {
        "Script": 4,
        "Fetch": 2,
        "Image": 2
    },
    "nameservers": [
        "ns-1484.awsdns-57.org",
        "ns-1949.awsdns-51.co.uk",
        "ns-409.awsdns-51.com",
        "ns-609.awsdns-12.net"
    ]
}