{
    "domain": "bizible.com",
    "owner": {
        "name": "Adobe Inc.",
        "displayName": "Adobe",
        "privacyPolicy": "https://www.adobe.com/privacy/marketing-cloud.html",
        "url": "http://adobe.com"
    },
    "source": [
        "DuckDuckGo-CA"
    ],
    "prevalence": 0.00167,
    "sites": 16,
    "subdomains": [
        "cdn"
    ],
    "cnames": [],
    "fingerprinting": 1,
    "resources": [
        {
            "rule": "bizible\\.com\\/scripts\\/bizible\\.js",
            "cookies": 0.00146,
            "fingerprinting": 1,
            "subdomains": [
                "cdn"
            ],
            "apis": {
                "Navigator.prototype.userAgent": 8,
                "Document.cookie getter": 14,
                "Date.prototype.getTime": 14,
                "Document.cookie setter": 14,
                "Screen.prototype.width": 11,
                "Screen.prototype.height": 11,
                "Notification.permission": 1,
                "Navigator.prototype.plugins": 1
            },
            "sites": 15,
            "prevalence": 0.00157,
            "cnames": [],
            "responseHashes": [
                "42bb2b975f7890325246797a91d8e64ce04ccc73a4bb4c29e30fc1e4cd4ca841"
            ],
            "type": "Script",
            "firstPartyCookies": {
                "_biz_dfsA": {
                    "ttl": -55,
                    "length": 4,
                    "prevalence": 0.0012549675800041832,
                    "uniqueness": 0.08333333333333333
                },
                "_biz_kvpA": {
                    "ttl": -53,
                    "length": 4,
                    "prevalence": 0.001150386948337168,
                    "uniqueness": 0.09090909090909091
                },
                "_biz_uid": {
                    "ttl": 31536007,
                    "length": 30,
                    "prevalence": 0.0012549675800041832,
                    "uniqueness": 1
                },
                "_biz_nA": {
                    "ttl": 31536006,
                    "length": 1,
                    "prevalence": 0.0014641288433382138,
                    "uniqueness": 0.2857142857142857
                },
                "_biz_pendingA": {
                    "ttl": 31536006,
                    "length": 27,
                    "prevalence": 0.0014641288433382138,
                    "uniqueness": 0.21428571428571427
                },
                "_biz_flagsA": {
                    "ttl": 31536007,
                    "length": 97,
                    "prevalence": 0.0013595482116711985,
                    "uniqueness": 0.6923076923076923
                },
                "_biz_ABTestA": {
                    "ttl": 31536001,
                    "length": 11,
                    "prevalence": 0.00020916126333403055,
                    "uniqueness": 1
                },
                "_biz_EventA": {
                    "ttl": -59,
                    "length": 4,
                    "prevalence": 0.00010458063166701528,
                    "uniqueness": 1
                },
                "_biz_sid": {
                    "ttl": -59,
                    "length": 4,
                    "prevalence": 0.00010458063166701528,
                    "uniqueness": 1
                }
            },
            "firstPartyCookiesSent": {},
            "exampleSites": [
                "gitlab.com",
                "developer.nvidia.com",
                "docs.gitlab.com",
                "docs.nvidia.com",
                "grabcad.com",
                "pitchbook.com",
                "www.anaconda.com",
                "www.cloudflare.com",
                "www.cvent.com",
                "www.logitech.com",
                "www.nasdaq.com",
                "www.payscale.com",
                "www.smartsheet.com",
                "www.sqlservercentral.com",
                "www.weareteachers.com"
            ]
        },
        {
            "rule": "bizible\\.com\\/ipv",
            "cookies": 0.00146,
            "fingerprinting": 0,
            "subdomains": [
                "cdn"
            ],
            "apis": {},
            "sites": 14,
            "prevalence": 0.00146,
            "cnames": [],
            "responseHashes": [
                "6b3da89922d333d106b84fefeebd7b16bfebf4cfbd7bef37fa10a47c471ae64c"
            ],
            "type": "Image",
            "firstPartyCookies": {},
            "firstPartyCookiesSent": {
                "_biz_uid": 0.001150386948337168,
                "SESSlsd": 0.00010458063166701528,
                "lotame_domain_check": 0.00010458063166701528
            },
            "exampleSites": [
                "gitlab.com",
                "developer.nvidia.com",
                "docs.gitlab.com",
                "docs.nvidia.com",
                "grabcad.com",
                "pitchbook.com",
                "www.anaconda.com",
                "www.cloudflare.com",
                "www.cvent.com",
                "www.logitech.com",
                "www.nasdaq.com",
                "www.payscale.com",
                "www.smartsheet.com",
                "www.weareteachers.com"
            ]
        },
        {
            "rule": "bizible\\.com\\/xdc\\.js",
            "cookies": 0,
            "fingerprinting": 0,
            "subdomains": [
                "cdn"
            ],
            "apis": {},
            "sites": 14,
            "prevalence": 0.00146,
            "cnames": [],
            "responseHashes": [
                "6d22e660ead72f14b0aa8e3dfc8de1da35f17e3559b489e00692f15f50faa1a6",
                "9347e8cdc34a181fc9f3fcbe7d9a005ddd7b0f44f2196d0f79d238727b3891a1",
                "adfd7dcf5fce6fcce445a2debbb78056ca5d6488e369c7ed7b28a63bab07c8f8",
                "ebf26b953806ebc441888d9f85991a54af7b44b5cc30914f8d0182a4e13df848",
                "b2df6462a8f8173d69a9ac138f9bd1ffcf99f0747d7efa24c64a849e1e0ac9f0",
                "0d3c2686c4cc54cdb567d88fb82a1311f8db7a012ef4be3e0fe63fd9e54be615",
                "ade5048ac452382ee0b7ca9aec6a3c6f0e898e0991dbdc64a6d8f48872abe6af",
                "db4cf5b582e098bd63e35d06f827d7b4cd902681df765a9233130a80ed340939",
                "ee36f8a6a937c96b1ed5e2cfaf880663cba0194f8d090b51af719f308c369571",
                "009d0689e8e5a6224f7f6b1b597b68252fafc169c8a56f24d66913814bc5209c",
                "dfffdfffc33923ed564af07fba8556293191ebe289d0a2fd5af48a1c2c8b1169"
            ],
            "type": "Script",
            "firstPartyCookies": {},
            "firstPartyCookiesSent": {
                "_biz_uid": 0.001150386948337168
            },
            "exampleSites": [
                "gitlab.com",
                "developer.nvidia.com",
                "docs.gitlab.com",
                "docs.nvidia.com",
                "grabcad.com",
                "pitchbook.com",
                "www.anaconda.com",
                "www.cloudflare.com",
                "www.cvent.com",
                "www.logitech.com",
                "www.nasdaq.com",
                "www.payscale.com",
                "www.smartsheet.com",
                "www.weareteachers.com"
            ]
        },
        {
            "rule": "bizible\\.com\\/u",
            "cookies": 0,
            "fingerprinting": 0,
            "subdomains": [
                "cdn"
            ],
            "apis": {},
            "sites": 12,
            "prevalence": 0.00125,
            "cnames": [],
            "responseHashes": [
                "6b3da89922d333d106b84fefeebd7b16bfebf4cfbd7bef37fa10a47c471ae64c"
            ],
            "type": "Image",
            "firstPartyCookies": {},
            "firstPartyCookiesSent": {
                "SESSlsd": 0.00020916126333403055,
                "_biz_uid": 0.0009412256850031374,
                "lotame_domain_check": 0.00010458063166701528
            },
            "exampleSites": [
                "nvidia.com",
                "developer.nvidia.com",
                "docs.gitlab.com",
                "docs.nvidia.com",
                "grabcad.com",
                "pitchbook.com",
                "www.anaconda.com",
                "www.cloudflare.com",
                "www.cvent.com",
                "www.logitech.com",
                "www.nasdaq.com",
                "www.payscale.com"
            ]
        }
    ],
    "categories": [],
    "performance": {},
    "cookies": 0.00167,
    "topInitiators": [
        {
            "domain": "first party",
            "prevalence": 0.39285714285714285
        },
        {
            "domain": "cookielaw.org",
            "prevalence": 0.2857142857142857
        },
        {
            "domain": "logr-ingest.com",
            "prevalence": 0.10714285714285714
        },
        {
            "domain": "googletagmanager.com",
            "prevalence": 0.10714285714285714
        },
        {
            "domain": "adobedtm.com",
            "prevalence": 0.07142857142857142
        },
        {
            "domain": "optimizely.com",
            "prevalence": 0.03571428571428571
        }
    ],
    "types": {
        "Script": 29,
        "Image": 26
    },
    "nameservers": [
        "ns201.adobe.net",
        "ns204.adobe.net",
        "ns203.adobe.net",
        "ns206.adobe.net",
        "ns205.adobe.net",
        "ns202.adobe.net"
    ]
}