{
    "domain": "refinery89.com",
    "owner": {},
    "source": [
        "DuckDuckGo-NO"
    ],
    "prevalence": 0.000614,
    "sites": 6,
    "subdomains": [
        "tags"
    ],
    "cnames": [],
    "fingerprinting": 2,
    "resources": [
        {
            "rule": "refinery89\\.com\\/demandTiersFloors\\.json",
            "cookies": 0,
            "fingerprinting": 0,
            "subdomains": [
                "tags"
            ],
            "apis": {},
            "sites": 6,
            "prevalence": 0.000614,
            "cnames": [],
            "responseHashes": [
                "8478981363831cb5f83b17b66aec7ce9936152468cfee784e86ef5ecbd37b2b5"
            ],
            "type": "Fetch",
            "firstPartyCookies": {},
            "firstPartyCookiesSent": {},
            "exampleSites": [
                "alleantworten.de",
                "www.aidedd.org",
                "www.filmaffinity.com",
                "www.isteshaltbar.de",
                "www.procyclingstats.com",
                "www.valutakalkulator.net"
            ]
        },
        {
            "rule": "refinery89\\.com\\/prebid\\/prebid9\\.35\\.js",
            "cookies": 0,
            "fingerprinting": 1,
            "subdomains": [
                "tags"
            ],
            "apis": {
                "NavigatorUAData.prototype.brands": 2,
                "NavigatorUAData.prototype.platform": 2,
                "window.sessionStorage": 2,
                "Navigator.prototype.userAgent": 2,
                "Notification.permission": 2,
                "Navigator.prototype.plugins": 2
            },
            "sites": 6,
            "prevalence": 0.000614,
            "cnames": [],
            "responseHashes": [
                "1f472d2c96b1c8c282c308d84145cc791104a3584ff2b8e2ea0189815dc45e36"
            ],
            "type": "Script",
            "firstPartyCookies": {},
            "firstPartyCookiesSent": {},
            "exampleSites": [
                "alleantworten.de",
                "www.aidedd.org",
                "www.filmaffinity.com",
                "www.isteshaltbar.de",
                "www.procyclingstats.com",
                "www.valutakalkulator.net"
            ]
        },
        {
            "rule": "refinery89\\.com\\/video\\/js\\/videoPlayerHelperRaw\\.js",
            "cookies": 0,
            "fingerprinting": 0,
            "subdomains": [
                "tags"
            ],
            "apis": {},
            "sites": 3,
            "prevalence": 0.000307,
            "cnames": [],
            "responseHashes": [
                "948d19ef43736b9714a7129585e2e5978c515590f7085ce5ee97f83a63d2a973"
            ],
            "type": "Script",
            "firstPartyCookies": {},
            "firstPartyCookiesSent": {},
            "exampleSites": [
                "alleantworten.de",
                "www.filmaffinity.com",
                "www.isteshaltbar.de"
            ]
        },
        {
            "rule": "refinery89\\.com\\/video\\/css\\/r89-video-outstream-styles\\.min\\.css",
            "cookies": 0,
            "fingerprinting": 0,
            "subdomains": [
                "tags"
            ],
            "apis": {},
            "sites": 3,
            "prevalence": 0.000307,
            "cnames": [],
            "responseHashes": [
                "9e442332afbc62cc5031bb4f60ed9695a15963bde285848f25195dcee455f2ed"
            ],
            "type": "Stylesheet",
            "firstPartyCookies": {},
            "firstPartyCookiesSent": {},
            "exampleSites": [
                "alleantworten.de",
                "www.filmaffinity.com",
                "www.isteshaltbar.de"
            ]
        },
        {
            "rule": "refinery89\\.com\\/video\\/css\\/r89-video-overlay-styles\\.min\\.css",
            "cookies": 0,
            "fingerprinting": 0,
            "subdomains": [
                "tags"
            ],
            "apis": {},
            "sites": 3,
            "prevalence": 0.000307,
            "cnames": [],
            "responseHashes": [
                "7af4821557228a869650eea67b8e0d81e47d237e5f44b25c290829a07d9a718f"
            ],
            "type": "Stylesheet",
            "firstPartyCookies": {},
            "firstPartyCookiesSent": {},
            "exampleSites": [
                "alleantworten.de",
                "www.filmaffinity.com",
                "www.isteshaltbar.de"
            ]
        },
        {
            "rule": "refinery89\\.com\\/prebid_check\\.js",
            "cookies": 0,
            "fingerprinting": 0,
            "subdomains": [
                "tags"
            ],
            "apis": {},
            "sites": 6,
            "prevalence": 0.000614,
            "cnames": [],
            "responseHashes": [
                "0cfd7fdc6e608bc2820e86aa254d06fd2b5142fbf945626c03404a86a65fe4cb"
            ],
            "type": "Script",
            "firstPartyCookies": {},
            "firstPartyCookiesSent": {},
            "exampleSites": [
                "alleantworten.de",
                "www.aidedd.org",
                "www.filmaffinity.com",
                "www.isteshaltbar.de",
                "www.procyclingstats.com",
                "www.valutakalkulator.net"
            ]
        }
    ],
    "categories": [],
    "performance": {},
    "cookies": 0,
    "topInitiators": [
        {
            "domain": "first party",
            "prevalence": 1
        }
    ],
    "types": {
        "Fetch": 6,
        "Script": 15,
        "Stylesheet": 6
    },
    "nameservers": [
        "ns1.transip.nl",
        "ns0.transip.net",
        "ns2.transip.eu"
    ]
}