{
    "domain": "cludo.com",
    "owner": {},
    "source": [
        "DuckDuckGo-US"
    ],
    "prevalence": 0.00154,
    "sites": 218,
    "subdomains": [
        "customer",
        "api-us1",
        "api"
    ],
    "cnames": [],
    "fingerprinting": 1,
    "resources": [
        {
            "rule": "cludo\\.com\\/scripts\\/bundles\\/search-script\\.min\\.js",
            "cookies": 0,
            "fingerprinting": 1,
            "subdomains": [
                "customer"
            ],
            "apis": {
                "window.localStorage": 96,
                "Navigator.prototype.userAgent": 84,
                "Navigator.prototype.appVersion": 88
            },
            "sites": 131,
            "prevalence": 0.000927,
            "cnames": [],
            "responseHashes": [
                "e7fe78a1c72072ba42de9dace35487be844644e7c2e299ad4c11a1d3ff5d1805"
            ],
            "type": "Script",
            "firstPartyCookies": {},
            "firstPartyCookiesSent": {},
            "exampleSites": [
                "www.dutchessny.gov",
                "www.centralbedfordshire.gov.uk",
                "lawyers.findlaw.com",
                "www.gundogmag.com",
                "www.applefcu.org",
                "johnsonoutdoors.com",
                "www.business.att.com",
                "www.oneblood.org",
                "constitution.findlaw.com",
                "www.parkinsons.org.uk",
                "washu.edu",
                "umbrella.cisco.com",
                "www.dtcc.edu",
                "www.calbanktrust.com",
                "www.chesapeakebay.net",
                "www.scdmvonline.com",
                "www.twdb.texas.gov",
                "santaclarita.gov",
                "scdmvonline.com",
                "www.aeldresagen.dk"
            ]
        },
        {
            "rule": "cludo\\.com\\/api\\/v3\\/10000331\\/10002311\\/autocomplete",
            "cookies": 0,
            "fingerprinting": 0,
            "subdomains": [
                "api-us1"
            ],
            "apis": {},
            "sites": 2,
            "prevalence": 0.0000141,
            "cnames": [],
            "responseHashes": [],
            "type": "Preflight",
            "firstPartyCookies": {},
            "firstPartyCookiesSent": {},
            "exampleSites": [
                "superlawyers.com",
                "profiles.superlawyers.com"
            ]
        },
        {
            "rule": "cludo\\.com\\/api\\/v3\\/10000331\\/10002311\\/autocomplete",
            "cookies": 0,
            "fingerprinting": 0,
            "subdomains": [
                "api-us1"
            ],
            "apis": {},
            "sites": 2,
            "prevalence": 0.0000141,
            "cnames": [],
            "responseHashes": [
                "c32ea022e9b731487e0bf9621282669420e8850313e7504d2b3b269cf909e241"
            ],
            "type": "Fetch",
            "firstPartyCookies": {},
            "firstPartyCookiesSent": {},
            "exampleSites": [
                "superlawyers.com",
                "profiles.superlawyers.com"
            ]
        },
        {
            "rule": "cludo\\.com\\/css\\/templates\\/v1\\.1\\/essentials\\/cludo-search\\.min\\.css",
            "cookies": 0,
            "fingerprinting": 0,
            "subdomains": [
                "customer"
            ],
            "apis": {},
            "sites": 11,
            "prevalence": 0.0000778,
            "cnames": [],
            "responseHashes": [
                "2ee7ce67663b74bd50e4afbf63071bf69e3fd258736d25eb02e7eb0214944378"
            ],
            "type": "Stylesheet",
            "firstPartyCookies": {},
            "firstPartyCookiesSent": {},
            "exampleSites": [
                "bellevuewa.gov",
                "www.deltadentalmn.org",
                "www.freightliner.com",
                "www.kornferry.com",
                "www.larimer.gov",
                "www.lmcu.org",
                "www.lvvwd.com",
                "www.nebraskablue.com",
                "www.pluralsight.com",
                "www.smsu.edu",
                "www.texasattorneygeneral.gov"
            ]
        },
        {
            "rule": "cludo\\.com\\/css\\/templates\\/v2\\.1\\/essentials\\/cludo-search\\.min\\.css",
            "cookies": 0,
            "fingerprinting": 0,
            "subdomains": [
                "customer"
            ],
            "apis": {},
            "sites": 33,
            "prevalence": 0.000233,
            "cnames": [],
            "responseHashes": [
                "e8bb034aae969d51e8330c20569601c6017d4679fa3f39f5fad6d258d3c49151"
            ],
            "type": "Stylesheet",
            "firstPartyCookies": {},
            "firstPartyCookiesSent": {},
            "exampleSites": [
                "www.glo.texas.gov",
                "santaclarita.gov",
                "www.bobcat.com",
                "www.augusta.edu",
                "www.broward.edu",
                "www.oneblood.org",
                "umbrella.cisco.com",
                "scdmvonline.com",
                "www.ruokavirasto.fi",
                "www.dtcc.edu",
                "www.commonwealthu.edu",
                "www.jefferson.kyschools.us",
                "www.jackson.com",
                "www.hematology.org",
                "blazecu.com",
                "www.palomar.edu",
                "www.scdmvonline.com",
                "duo.com",
                "www.schoolsfirstfcu.org",
                "myfwc.com"
            ]
        },
        {
            "rule": "cludo\\.com\\/templates\\/369\\/14017\\/dist\\/styles\\/cludo-search-results\\.css",
            "cookies": 0,
            "fingerprinting": 0,
            "subdomains": [
                "customer"
            ],
            "apis": {},
            "sites": 2,
            "prevalence": 0.0000141,
            "cnames": [],
            "responseHashes": [
                "8c1a77484fe4cc2d51f2dadfec5e32c702439e3bbec59db6511845b42ad55a9a"
            ],
            "type": "Stylesheet",
            "firstPartyCookies": {},
            "firstPartyCookiesSent": {},
            "exampleSites": [
                "claris.com",
                "community.claris.com"
            ]
        },
        {
            "rule": "cludo\\.com\\/templates\\/369\\/14017\\/dist\\/js\\/cludo-search-results\\.js",
            "cookies": 0,
            "fingerprinting": 0,
            "subdomains": [
                "customer"
            ],
            "apis": {},
            "sites": 2,
            "prevalence": 0.0000141,
            "cnames": [],
            "responseHashes": [
                "2a09911c4a5c4ff3c1da38247cf43b684a54bea9c6cc0756caaa51c1eabad544"
            ],
            "type": "Script",
            "firstPartyCookies": {},
            "firstPartyCookiesSent": {},
            "exampleSites": [
                "claris.com",
                "community.claris.com"
            ]
        },
        {
            "rule": "cludo\\.com\\/scripts\\/bundles\\/experiences\\/manager\\.js",
            "cookies": 0,
            "fingerprinting": 0,
            "subdomains": [
                "customer"
            ],
            "apis": {},
            "sites": 3,
            "prevalence": 0.0000212,
            "cnames": [],
            "responseHashes": [
                "173a5721498e980457add97a9f89fc6157ac67c6fbca95ef6440877a5c678c09"
            ],
            "type": "Script",
            "firstPartyCookies": {},
            "firstPartyCookiesSent": {},
            "exampleSites": [
                "claris.com",
                "community.claris.com",
                "www.vero.fi"
            ]
        },
        {
            "rule": "cludo\\.com\\/api\\/v3\\/369\\/14017\\/websites\\/publicsettings",
            "cookies": 0,
            "fingerprinting": 0,
            "subdomains": [
                "api"
            ],
            "apis": {},
            "sites": 2,
            "prevalence": 0.0000141,
            "cnames": [],
            "responseHashes": [],
            "type": "Preflight",
            "firstPartyCookies": {},
            "firstPartyCookiesSent": {},
            "exampleSites": [
                "claris.com",
                "community.claris.com"
            ]
        },
        {
            "rule": "cludo\\.com\\/api\\/v3\\/369\\/14017\\/websites\\/publicsettings",
            "cookies": 0,
            "fingerprinting": 0,
            "subdomains": [
                "api"
            ],
            "apis": {},
            "sites": 2,
            "prevalence": 0.0000141,
            "cnames": [],
            "responseHashes": [
                "67136621ca566ce86b9613a532cc381bcd8b891871735859e78c31834b72c4df"
            ],
            "type": "XHR",
            "firstPartyCookies": {},
            "firstPartyCookiesSent": {},
            "exampleSites": [
                "claris.com",
                "community.claris.com"
            ]
        },
        {
            "rule": "cludo\\.com\\/api\\/v4\\/369\\/experiences\\/settings",
            "cookies": 0,
            "fingerprinting": 0,
            "subdomains": [
                "api"
            ],
            "apis": {},
            "sites": 2,
            "prevalence": 0.0000141,
            "cnames": [],
            "responseHashes": [
                "4f53cda18c2baa0c0354bb5f9a3ecbe5ed12ab4d8e11ba873c2f11161202b945"
            ],
            "type": "Fetch",
            "firstPartyCookies": {},
            "firstPartyCookiesSent": {},
            "exampleSites": [
                "claris.com",
                "community.claris.com"
            ]
        },
        {
            "rule": "cludo\\.com\\/assets\\/10000002\\/10000002\\/cludo-search\\.min\\.css",
            "cookies": 0,
            "fingerprinting": 0,
            "subdomains": [
                "customer"
            ],
            "apis": {},
            "sites": 3,
            "prevalence": 0.0000212,
            "cnames": [],
            "responseHashes": [
                "09c88cacfa9300bb4bec34d1fc68f370f5fd77d3b1838b0449a74cef03c214a5"
            ],
            "type": "Stylesheet",
            "firstPartyCookies": {},
            "firstPartyCookiesSent": {},
            "exampleSites": [
                "trugreen.com",
                "myaccountqa.trugreen.com",
                "www.trugreen.com"
            ]
        },
        {
            "rule": "cludo\\.com\\/scripts\\/bundles\\/analytics\\/1\\.0\\.3\\/cludo-statistics\\.app\\.js",
            "cookies": 0,
            "fingerprinting": 1,
            "subdomains": [
                "customer"
            ],
            "apis": {
                "Navigator.prototype.userAgent": 2
            },
            "sites": 2,
            "prevalence": 0.0000141,
            "cnames": [],
            "responseHashes": [
                "6864da43664c6fe8117e72dda8ea46d1bbfefab8a65063d078ee40b4a84b9444"
            ],
            "type": "Script",
            "firstPartyCookies": {},
            "firstPartyCookiesSent": {},
            "exampleSites": [
                "dinoffentligetransport.dk",
                "www.discprofile.com"
            ]
        },
        {
            "rule": "cludo\\.com\\/css\\/405\\/2001\\/cludo-search\\.min\\.css",
            "cookies": 0,
            "fingerprinting": 0,
            "subdomains": [
                "customer"
            ],
            "apis": {},
            "sites": 2,
            "prevalence": 0.0000141,
            "cnames": [],
            "responseHashes": [
                "8e1911405987e195fcaccc6cc8abaa570ad96cf1c5ca27fd9e26ffa2f455c27c"
            ],
            "type": "Stylesheet",
            "firstPartyCookies": {},
            "firstPartyCookiesSent": {},
            "exampleSites": [
                "dutchessny.gov",
                "www.dutchessny.gov"
            ]
        },
        {
            "rule": "cludo\\.com\\/assets\\/font-icons\\/css\\/all\\.css",
            "cookies": 0,
            "fingerprinting": 0,
            "subdomains": [
                "customer"
            ],
            "apis": {},
            "sites": 4,
            "prevalence": 0.0000283,
            "cnames": [],
            "responseHashes": [
                "953f2162ecd5182d2b8d73a5939cab53a1963c3c8d0dfe381667d0d5716b6ea0"
            ],
            "type": "Stylesheet",
            "firstPartyCookies": {},
            "firstPartyCookiesSent": {},
            "exampleSites": [
                "hojskolesangbogen.dk",
                "www.browning.com",
                "www.ramseycounty.us",
                "www.tpg.com.au"
            ]
        },
        {
            "rule": "cludo\\.com\\/assets\\/10000789\\/10001198\\/cludo-search-d9\\.min\\.css",
            "cookies": 0,
            "fingerprinting": 0,
            "subdomains": [
                "customer"
            ],
            "apis": {},
            "sites": 2,
            "prevalence": 0.0000141,
            "cnames": [],
            "responseHashes": [
                "ff7e7a5a536e70fa72d456ca4f209f7dc9aef2ab0cc718dc945d42b1ae7df8de"
            ],
            "type": "Stylesheet",
            "firstPartyCookies": {},
            "firstPartyCookiesSent": {},
            "exampleSites": [
                "johnsonoutdoors.com",
                "humminbird.johnsonoutdoors.com"
            ]
        },
        {
            "rule": "cludo\\.com\\/assets\\/10000789\\/10001198\\/cludo-helper-d9\\.js",
            "cookies": 0,
            "fingerprinting": 0,
            "subdomains": [
                "customer"
            ],
            "apis": {},
            "sites": 2,
            "prevalence": 0.0000141,
            "cnames": [],
            "responseHashes": [
                "ea26bf2b213b930ded3e8c84795ae649346f9beb025f9c09791282aa3b61031a"
            ],
            "type": "Script",
            "firstPartyCookies": {},
            "firstPartyCookiesSent": {},
            "exampleSites": [
                "johnsonoutdoors.com",
                "humminbird.johnsonoutdoors.com"
            ]
        },
        {
            "rule": "cludo\\.com\\/assets\\/10000789\\/10001197\\/cludo-search-d9\\.min\\.css",
            "cookies": 0,
            "fingerprinting": 0,
            "subdomains": [
                "customer"
            ],
            "apis": {},
            "sites": 2,
            "prevalence": 0.0000141,
            "cnames": [],
            "responseHashes": [
                "31bfe8dca8959c49deecee98a78ae26a6e19b1702b6c078efaf1fe8a3c2af10e"
            ],
            "type": "Stylesheet",
            "firstPartyCookies": {},
            "firstPartyCookiesSent": {},
            "exampleSites": [
                "johnsonoutdoors.com",
                "minnkota.johnsonoutdoors.com"
            ]
        },
        {
            "rule": "cludo\\.com\\/assets\\/10000789\\/10001197\\/cludo-helper-d9\\.js",
            "cookies": 0,
            "fingerprinting": 0,
            "subdomains": [
                "customer"
            ],
            "apis": {},
            "sites": 2,
            "prevalence": 0.0000141,
            "cnames": [],
            "responseHashes": [
                "e999ddbfd8b6290339f7c36834ecbfa515ec104f9c9ee4cb07b5b81014a1f526"
            ],
            "type": "Script",
            "firstPartyCookies": {},
            "firstPartyCookiesSent": {},
            "exampleSites": [
                "johnsonoutdoors.com",
                "minnkota.johnsonoutdoors.com"
            ]
        },
        {
            "rule": "cludo\\.com\\/css\\/overlay\\/cludo-search-default\\.min\\.css",
            "cookies": 0,
            "fingerprinting": 0,
            "subdomains": [
                "customer"
            ],
            "apis": {},
            "sites": 11,
            "prevalence": 0.0000778,
            "cnames": [],
            "responseHashes": [
                "e005e6fb02f74d6cdbfdbf3db38141e77bcf302de1403140ac2084b1d3ae0719"
            ],
            "type": "Stylesheet",
            "firstPartyCookies": {},
            "firstPartyCookiesSent": {},
            "exampleSites": [
                "nuvisionfederal.com",
                "web2.acbl.org",
                "www.acbl.org",
                "www.americancentury.com",
                "www.awcwire.com",
                "www.chesapeakebay.net",
                "www.granddesignrv.com",
                "www.nicklauschildrens.org",
                "www.nylaarp.com",
                "www.sarasotacountyschools.net",
                "www.topsmarkets.com"
            ]
        },
        {
            "rule": "cludo\\.com\\/assets\\/10000789\\/10001196\\/cludo-search-d9\\.min\\.css",
            "cookies": 0,
            "fingerprinting": 0,
            "subdomains": [
                "customer"
            ],
            "apis": {},
            "sites": 2,
            "prevalence": 0.0000141,
            "cnames": [],
            "responseHashes": [
                "b2e7ff4796620f506b940928d028771e400102fb48f569186695048b98ba2ac2"
            ],
            "type": "Stylesheet",
            "firstPartyCookies": {},
            "firstPartyCookiesSent": {},
            "exampleSites": [
                "johnsonoutdoors.com",
                "oldtownwatercraft.johnsonoutdoors.com"
            ]
        },
        {
            "rule": "cludo\\.com\\/assets\\/10000789\\/10001196\\/cludo-helper-d9\\.js",
            "cookies": 0,
            "fingerprinting": 0,
            "subdomains": [
                "customer"
            ],
            "apis": {},
            "sites": 2,
            "prevalence": 0.0000141,
            "cnames": [],
            "responseHashes": [
                "f45742aebbfb5934f424acfdc383c3067971893f68ea4db0cfc2645aa6a5a03f"
            ],
            "type": "Script",
            "firstPartyCookies": {},
            "firstPartyCookiesSent": {},
            "exampleSites": [
                "johnsonoutdoors.com",
                "oldtownwatercraft.johnsonoutdoors.com"
            ]
        },
        {
            "rule": "cludo\\.com\\/assets\\/10000789\\/10001193\\/cludo-search-d9\\.min\\.css",
            "cookies": 0,
            "fingerprinting": 0,
            "subdomains": [
                "customer"
            ],
            "apis": {},
            "sites": 2,
            "prevalence": 0.0000141,
            "cnames": [],
            "responseHashes": [
                "2f551983905d04f5276b0729a7de5e9f1fc36b2fc1fa1a666d9fd64aabd74b8c"
            ],
            "type": "Stylesheet",
            "firstPartyCookies": {},
            "firstPartyCookiesSent": {},
            "exampleSites": [
                "johnsonoutdoors.com",
                "scubapro.johnsonoutdoors.com"
            ]
        },
        {
            "rule": "cludo\\.com\\/assets\\/10000789\\/10001193\\/cludo-helper-d9\\.js",
            "cookies": 0,
            "fingerprinting": 0,
            "subdomains": [
                "customer"
            ],
            "apis": {},
            "sites": 2,
            "prevalence": 0.0000141,
            "cnames": [],
            "responseHashes": [
                "f0aabd13cd92e7b67c058c65d33f6fdd250925aecbba93c567a27b2beb18dcc5"
            ],
            "type": "Script",
            "firstPartyCookies": {},
            "firstPartyCookiesSent": {},
            "exampleSites": [
                "johnsonoutdoors.com",
                "scubapro.johnsonoutdoors.com"
            ]
        },
        {
            "rule": "cludo\\.com\\/scripts\\/bundles\\/search-script\\.js",
            "cookies": 0,
            "fingerprinting": 1,
            "subdomains": [
                "customer"
            ],
            "apis": {
                "window.localStorage": 9,
                "Navigator.prototype.userAgent": 7,
                "Navigator.prototype.appVersion": 9
            },
            "sites": 14,
            "prevalence": 0.000099,
            "cnames": [],
            "responseHashes": [
                "a76df20796d6637fa1b5f0c0f306ffe8c674edf8bb204cbf41941efeadedb5e1"
            ],
            "type": "Script",
            "firstPartyCookies": {},
            "firstPartyCookiesSent": {},
            "exampleSites": [
                "ashcroft.com",
                "www.cgsmedicare.com",
                "www.helsinki.fi",
                "www.hertfordshire.gov.uk",
                "www.islington.gov.uk",
                "www.opendns.com",
                "www.ramsayhealth.co.uk",
                "www.ramseycounty.us",
                "www.reading.gov.uk",
                "www.tpg.com.au",
                "www.trendmicro.com",
                "www.uvm.dk",
                "www.visitscotland.com",
                "www.westga.edu"
            ]
        },
        {
            "rule": "cludo\\.com\\/assets\\/10001401\\/10002305\\/cludo-search\\.min\\.css",
            "cookies": 0,
            "fingerprinting": 0,
            "subdomains": [
                "customer"
            ],
            "apis": {},
            "sites": 2,
            "prevalence": 0.0000141,
            "cnames": [],
            "responseHashes": [
                "e258acf1ced6124a170b319c951c60454cc91ff3dc1c59b7f9200a9ddcc113f2"
            ],
            "type": "Stylesheet",
            "firstPartyCookies": {},
            "firstPartyCookiesSent": {},
            "exampleSites": [
                "browning.com",
                "www.browning.com"
            ]
        },
        {
            "rule": "cludo\\.com\\/assets\\/10001401\\/10002305\\/cludo-search\\.js",
            "cookies": 0,
            "fingerprinting": 0,
            "subdomains": [
                "customer"
            ],
            "apis": {},
            "sites": 2,
            "prevalence": 0.0000141,
            "cnames": [],
            "responseHashes": [
                "abc4a8e1fb3153911ae6b5256dbfea1f0a89e282f27109975a88c97893677d22"
            ],
            "type": "Script",
            "firstPartyCookies": {},
            "firstPartyCookiesSent": {},
            "exampleSites": [
                "browning.com",
                "www.browning.com"
            ]
        },
        {
            "rule": "cludo\\.com\\/api\\/v3\\/10001401\\/10002305\\/search",
            "cookies": 0,
            "fingerprinting": 0,
            "subdomains": [
                "api-us1"
            ],
            "apis": {},
            "sites": 2,
            "prevalence": 0.0000141,
            "cnames": [],
            "responseHashes": [
                "970fff58e6f02966f85d0585dee432e26ed82ac94395c7c09e59d90c06061b1d"
            ],
            "type": "XHR",
            "firstPartyCookies": {},
            "firstPartyCookiesSent": {},
            "exampleSites": [
                "browning.com",
                "www.browning.com"
            ]
        },
        {
            "rule": "cludo\\.com\\/assets\\/10000029\\/10001369\\/cludo-search\\.min\\.css",
            "cookies": 0,
            "fingerprinting": 0,
            "subdomains": [
                "customer"
            ],
            "apis": {},
            "sites": 3,
            "prevalence": 0.0000212,
            "cnames": [],
            "responseHashes": [
                "a3f2a16cb973d71bab5814714ebb4f514f9bbc3bb53bdbbed75a480f24fd4e9e"
            ],
            "type": "Stylesheet",
            "firstPartyCookies": {},
            "firstPartyCookiesSent": {},
            "exampleSites": [
                "att.com",
                "www.business.att.com",
                "www.firstnet.com"
            ]
        },
        {
            "rule": "cludo\\.com\\/scripts\\/404\\/cludo-404\\.js",
            "cookies": 0,
            "fingerprinting": 1,
            "subdomains": [
                "customer"
            ],
            "apis": {
                "Date.prototype.getTime": 2,
                "Screen.prototype.width": 2,
                "Screen.prototype.height": 2,
                "Navigator.prototype.userAgent": 2,
                "Navigator.prototype.language": 2,
                "window.sessionStorage": 1
            },
            "sites": 2,
            "prevalence": 0.0000141,
            "cnames": [],
            "responseHashes": [
                "b6e5707bd92e349711f273336cf796cbb7779afe153fafb9b575c1dc8f4a3593"
            ],
            "type": "Script",
            "firstPartyCookies": {},
            "firstPartyCookiesSent": {},
            "exampleSites": [
                "calor.co.uk",
                "www.virginia.edu"
            ]
        },
        {
            "rule": "cludo\\.com\\/img\\/cludo-overlay-search-powered-by-Cludo\\.png",
            "cookies": 0,
            "fingerprinting": 0,
            "subdomains": [
                "customer"
            ],
            "apis": {},
            "sites": 2,
            "prevalence": 0.0000141,
            "cnames": [],
            "responseHashes": [
                "f0f5a24032067e29e68f4666d8842d78832ed8051aeeda2a60abf1fb9ad050ed"
            ],
            "type": "Image",
            "firstPartyCookies": {},
            "firstPartyCookiesSent": {},
            "exampleSites": [
                "calor.co.uk",
                "www.virginia.edu"
            ]
        },
        {
            "rule": "cludo\\.com\\/templates\\/10001467\\/cat_2024\\/dist\\/styles\\/cludo-search-results\\.css",
            "cookies": 0,
            "fingerprinting": 0,
            "subdomains": [
                "customer"
            ],
            "apis": {},
            "sites": 2,
            "prevalence": 0.0000141,
            "cnames": [],
            "responseHashes": [
                "21e36ed72e168d72bde2430ab89b92f6bd188da35ab80c08104ef4b9e26577f0"
            ],
            "type": "Stylesheet",
            "firstPartyCookies": {},
            "firstPartyCookiesSent": {},
            "exampleSites": [
                "chesterfield.gov",
                "www.chesterfield.gov"
            ]
        },
        {
            "rule": "cludo\\.com\\/templates\\/10001467\\/cat_2024\\/dist\\/js\\/cludo-search-results\\.js",
            "cookies": 0,
            "fingerprinting": 0,
            "subdomains": [
                "customer"
            ],
            "apis": {},
            "sites": 2,
            "prevalence": 0.0000141,
            "cnames": [],
            "responseHashes": [
                "b307ae11bd81a56f3a09f64641ab107283f77ec40c102de3263ea74e80f6d543"
            ],
            "type": "Script",
            "firstPartyCookies": {},
            "firstPartyCookiesSent": {},
            "exampleSites": [
                "chesterfield.gov",
                "www.chesterfield.gov"
            ]
        },
        {
            "rule": "cludo\\.com\\/scripts\\/bundles\\/assistant\\/1\\.0\\.1\\/support-assistant\\.js",
            "cookies": 0,
            "fingerprinting": 0,
            "subdomains": [
                "customer"
            ],
            "apis": {},
            "sites": 2,
            "prevalence": 0.0000141,
            "cnames": [],
            "responseHashes": [
                "d00f6c4e875d986c19f5302930f2c83018ab57a5661c0e366cd767f2c0adbef7"
            ],
            "type": "Script",
            "firstPartyCookies": {},
            "firstPartyCookiesSent": {},
            "exampleSites": [
                "chesterfield.gov",
                "www.chesterfield.gov"
            ]
        },
        {
            "rule": "cludo\\.com\\/api\\/v3\\/10001467\\/10002516\\/websites\\/publicsettings",
            "cookies": 0,
            "fingerprinting": 0,
            "subdomains": [
                "api-us1"
            ],
            "apis": {},
            "sites": 2,
            "prevalence": 0.0000141,
            "cnames": [],
            "responseHashes": [
                "2006496f71cce9979bd7053811b76a08d30490acf9348d697003cb049f4d1de9"
            ],
            "type": "XHR",
            "firstPartyCookies": {},
            "firstPartyCookiesSent": {},
            "exampleSites": [
                "chesterfield.gov",
                "www.chesterfield.gov"
            ]
        },
        {
            "rule": "cludo\\.com\\/api\\/v3\\/10001467\\/10002516\\/websites\\/publicsettings",
            "cookies": 0,
            "fingerprinting": 0,
            "subdomains": [
                "api-us1"
            ],
            "apis": {},
            "sites": 2,
            "prevalence": 0.0000141,
            "cnames": [],
            "responseHashes": [],
            "type": "Preflight",
            "firstPartyCookies": {},
            "firstPartyCookiesSent": {},
            "exampleSites": [
                "chesterfield.gov",
                "www.chesterfield.gov"
            ]
        },
        {
            "rule": "cludo\\.com\\/scripts\\/bundles\\/assistant\\/1\\.0\\.1\\/cludo-search-results\\.css",
            "cookies": 0,
            "fingerprinting": 0,
            "subdomains": [
                "customer"
            ],
            "apis": {},
            "sites": 2,
            "prevalence": 0.0000141,
            "cnames": [],
            "responseHashes": [
                "496924192e1d7bc2833ecfa6e4adf25bcd2f81eea016f6eb6e93229be8c77d5d"
            ],
            "type": "Stylesheet",
            "firstPartyCookies": {},
            "firstPartyCookiesSent": {},
            "exampleSites": [
                "chesterfield.gov",
                "www.chesterfield.gov"
            ]
        },
        {
            "rule": "cludo\\.com\\/api\\/v3\\/-1\\/-1\\/websites\\/publicsettings",
            "cookies": 0,
            "fingerprinting": 0,
            "subdomains": [
                "api"
            ],
            "apis": {},
            "sites": 2,
            "prevalence": 0.0000141,
            "cnames": [],
            "responseHashes": [],
            "type": "Preflight",
            "firstPartyCookies": {},
            "firstPartyCookiesSent": {},
            "exampleSites": [
                "chesterfield.gov",
                "www.chesterfield.gov"
            ]
        },
        {
            "rule": "cludo\\.com\\/api\\/v3\\/-1\\/-1\\/websites\\/publicsettings",
            "cookies": 0,
            "fingerprinting": 0,
            "subdomains": [
                "api"
            ],
            "apis": {},
            "sites": 2,
            "prevalence": 0.0000141,
            "cnames": [],
            "responseHashes": [],
            "type": "XHR",
            "firstPartyCookies": {},
            "firstPartyCookiesSent": {},
            "exampleSites": [
                "chesterfield.gov",
                "www.chesterfield.gov"
            ]
        },
        {
            "rule": "cludo\\.com\\/assets\\/10000367\\/10000809\\/cludo-search\\.min\\.css",
            "cookies": 0,
            "fingerprinting": 0,
            "subdomains": [
                "customer"
            ],
            "apis": {},
            "sites": 12,
            "prevalence": 0.0000849,
            "cnames": [],
            "responseHashes": [
                "c39ac37fb7d57330c64b40dbd013d4c279b220b5be5f53df8484d46990eaa18a"
            ],
            "type": "Stylesheet",
            "firstPartyCookies": {},
            "firstPartyCookiesSent": {},
            "exampleSites": [
                "firearmsnews.com",
                "www.firearmsnews.com",
                "www.floridasportsman.com",
                "www.flyfisherman.com",
                "www.gameandfishmag.com",
                "www.gundogmag.com",
                "www.gunsandammo.com",
                "www.handgunsmag.com",
                "www.in-fisherman.com",
                "www.petersenshunting.com",
                "www.rifleshootermag.com",
                "www.shootingtimes.com"
            ]
        },
        {
            "rule": "cludo\\.com\\/assets\\/10000367\\/10000809\\/cludo-search\\.min\\.js",
            "cookies": 0,
            "fingerprinting": 1,
            "subdomains": [
                "customer"
            ],
            "apis": {
                "window.sessionStorage": 10
            },
            "sites": 12,
            "prevalence": 0.0000849,
            "cnames": [],
            "responseHashes": [
                "6126507a56bfa0d9fa93e738a8474b40f7b30d648982fb073052b1d4c6370730"
            ],
            "type": "Script",
            "firstPartyCookies": {},
            "firstPartyCookiesSent": {},
            "exampleSites": [
                "firearmsnews.com",
                "www.firearmsnews.com",
                "www.floridasportsman.com",
                "www.flyfisherman.com",
                "www.gameandfishmag.com",
                "www.gundogmag.com",
                "www.gunsandammo.com",
                "www.handgunsmag.com",
                "www.in-fisherman.com",
                "www.petersenshunting.com",
                "www.rifleshootermag.com",
                "www.shootingtimes.com"
            ]
        },
        {
            "rule": "cludo\\.com\\/css\\/504\\/8844\\/cludo-search\\.min\\.css",
            "cookies": 0,
            "fingerprinting": 0,
            "subdomains": [
                "customer"
            ],
            "apis": {},
            "sites": 2,
            "prevalence": 0.0000141,
            "cnames": [],
            "responseHashes": [
                "5a3a889c9262f1681511e3f1c00f9d835d18aa8e681d1f73d5c9b812f1fbdb02"
            ],
            "type": "Stylesheet",
            "firstPartyCookies": {},
            "firstPartyCookiesSent": {},
            "exampleSites": [
                "opendns.com",
                "www.opendns.com"
            ]
        },
        {
            "rule": "cludo\\.com\\/assets\\/10001301\\/10002130\\/cludo-search\\.min\\.css",
            "cookies": 0,
            "fingerprinting": 0,
            "subdomains": [
                "customer"
            ],
            "apis": {},
            "sites": 2,
            "prevalence": 0.0000141,
            "cnames": [],
            "responseHashes": [
                "10f547260af86972a192093d0524ebd4b5015e24f19f908d9d76e00af2e7e11e"
            ],
            "type": "Stylesheet",
            "firstPartyCookies": {},
            "firstPartyCookiesSent": {},
            "exampleSites": [
                "ramseycounty.us",
                "www.ramseycounty.us"
            ]
        },
        {
            "rule": "cludo\\.com\\/assets\\/10001301\\/10002130\\/cludo-search\\.js",
            "cookies": 0,
            "fingerprinting": 0,
            "subdomains": [
                "customer"
            ],
            "apis": {},
            "sites": 2,
            "prevalence": 0.0000141,
            "cnames": [],
            "responseHashes": [
                "f78483e347550d1ad0813d8861ebebdeda2274f219e756708bbf876d95cfaf76"
            ],
            "type": "Script",
            "firstPartyCookies": {},
            "firstPartyCookiesSent": {},
            "exampleSites": [
                "ramseycounty.us",
                "www.ramseycounty.us"
            ]
        },
        {
            "rule": "cludo\\.com\\/css\\/296\\/1798\\/cludo-search\\.min\\.css",
            "cookies": 0,
            "fingerprinting": 0,
            "subdomains": [
                "customer"
            ],
            "apis": {},
            "sites": 2,
            "prevalence": 0.0000141,
            "cnames": [],
            "responseHashes": [
                "676e66eeb5e721df2e68029d518067cece19d56d7e0b4a1c9a2e3c449a232bca"
            ],
            "type": "Stylesheet",
            "firstPartyCookies": {},
            "firstPartyCookiesSent": {},
            "exampleSites": [
                "trendmicro.com",
                "www.trendmicro.com"
            ]
        },
        {
            "rule": "cludo\\.com\\/assets\\/623\\/12809\\/cludo-helper\\.js",
            "cookies": 0,
            "fingerprinting": 0,
            "subdomains": [
                "customer"
            ],
            "apis": {},
            "sites": 2,
            "prevalence": 0.0000141,
            "cnames": [],
            "responseHashes": [
                "81f9335f0daba79fc46144520a99d12d40d1a47c4ab4164fffd9e7e299f1c31f"
            ],
            "type": "Script",
            "firstPartyCookies": {},
            "firstPartyCookiesSent": {},
            "exampleSites": [
                "visitscotland.com",
                "www.visitscotland.com"
            ]
        },
        {
            "rule": "cludo\\.com\\/api\\/v3\\/10001401\\/10002512\\/search",
            "cookies": 0,
            "fingerprinting": 0,
            "subdomains": [
                "api-us1"
            ],
            "apis": {},
            "sites": 2,
            "prevalence": 0.0000141,
            "cnames": [],
            "responseHashes": [
                "6e45e88b7443577e9b1dd32305e531a3d0793de6dc14e6b085e18d6d488b522d"
            ],
            "type": "XHR",
            "firstPartyCookies": {},
            "firstPartyCookiesSent": {},
            "exampleSites": [
                "winchesterguns.com",
                "www.winchesterguns.com"
            ]
        },
        {
            "rule": "cludo\\.com\\/assets\\/10000995\\/10001572\\/cludo-search\\.min\\.css",
            "cookies": 0,
            "fingerprinting": 0,
            "subdomains": [
                "customer"
            ],
            "apis": {},
            "sites": 2,
            "prevalence": 0.0000141,
            "cnames": [],
            "responseHashes": [
                "6e6b8f47c12104b0a35b77b3b00566500c129e16d512660d61f3a697a651f9e6"
            ],
            "type": "Stylesheet",
            "firstPartyCookies": {},
            "firstPartyCookiesSent": {},
            "exampleSites": [
                "worshiptogether.com",
                "www.worshiptogether.com"
            ]
        },
        {
            "rule": "cludo\\.com\\/assets\\/10000995\\/10001572\\/cludo-search\\.min\\.js",
            "cookies": 0,
            "fingerprinting": 0,
            "subdomains": [
                "customer"
            ],
            "apis": {},
            "sites": 2,
            "prevalence": 0.0000141,
            "cnames": [],
            "responseHashes": [
                "0bf7abb5061cdffceec8c7aa4919af15399b526ffc009e9f2721d44f239d3dd6"
            ],
            "type": "Script",
            "firstPartyCookies": {},
            "firstPartyCookiesSent": {},
            "exampleSites": [
                "worshiptogether.com",
                "www.worshiptogether.com"
            ]
        }
    ],
    "categories": [],
    "performance": {},
    "cookies": 0,
    "topInitiators": [
        {
            "domain": "first party",
            "prevalence": 0.975929978118162
        },
        {
            "domain": "msecnd.net",
            "prevalence": 0.006564551422319475
        },
        {
            "domain": "newrelic.com",
            "prevalence": 0.00437636761487965
        },
        {
            "domain": "azure.com",
            "prevalence": 0.00437636761487965
        },
        {
            "domain": "osano.com",
            "prevalence": 0.002188183807439825
        },
        {
            "domain": "cookiebot.com",
            "prevalence": 0.002188183807439825
        },
        {
            "domain": "apptegy.net",
            "prevalence": 0.002188183807439825
        },
        {
            "domain": "jquery.com",
            "prevalence": 0.002188183807439825
        }
    ],
    "types": {
        "Script": 186,
        "Preflight": 8,
        "Fetch": 4,
        "Stylesheet": 103,
        "XHR": 10,
        "Image": 2
    },
    "nameservers": [
        "ns-1957.awsdns-52.co.uk",
        "ns-399.awsdns-49.com",
        "ns-676.awsdns-20.net",
        "ns-1467.awsdns-55.org"
    ]
}