{
    "domain": "crucials.io",
    "owner": {},
    "source": [
        "DuckDuckGo-US"
    ],
    "prevalence": 0.0000212,
    "sites": 3,
    "subdomains": [
        "app"
    ],
    "cnames": [],
    "fingerprinting": 1,
    "resources": [
        {
            "rule": "crucials\\.io\\/script\\.js",
            "cookies": 0,
            "fingerprinting": 1,
            "subdomains": [
                "app"
            ],
            "apis": {
                "window.innerWidth": 2,
                "window.localStorage": 2,
                "Document.cookie getter": 2
            },
            "sites": 2,
            "prevalence": 0.0000141,
            "cnames": [],
            "responseHashes": [
                "124cf6788d034d809e017332a002943ef9c57082e867cbc6cf33db2ad7bddaf1"
            ],
            "type": "Script",
            "firstPartyCookies": {},
            "firstPartyCookiesSent": {},
            "exampleSites": [
                "gollihurmusic.com",
                "tanbooks.com"
            ]
        }
    ],
    "categories": [],
    "performance": {},
    "cookies": 0,
    "topInitiators": [
        {
            "domain": "first party",
            "prevalence": 1
        }
    ],
    "types": {
        "Script": 2
    },
    "nameservers": [
        "mustafa.ns.cloudflare.com",
        "tia.ns.cloudflare.com"
    ]
}