{
    "domain": "livejasmin.com",
    "owner": {
        "name": "DOCLER IP S.A R.L.",
        "displayName": "Docler IP"
    },
    "source": [
        "DuckDuckGo-US"
    ],
    "prevalence": 0.000304,
    "sites": 43,
    "subdomains": [
        "vast",
        "ccs",
        "crmapt"
    ],
    "cnames": [],
    "fingerprinting": 0,
    "resources": [
        {
            "rule": "livejasmin\\.com\\/",
            "cookies": 0,
            "fingerprinting": 0,
            "subdomains": [
                "vast"
            ],
            "apis": {},
            "sites": 25,
            "prevalence": 0.000177,
            "cnames": [],
            "responseHashes": [
                "70a1581b23014846a8fc1ff1d6672ed3532a67b069abe131fe6a55aa93b5ce75",
                "f7c13575029428e993d42250d99350baeb6e4616466d3dde6791b0bc30bdb55c",
                "a343eb6e9500dde2322cb22ed62da578ab5fc75f7297ecd9a62f455962a549e4",
                "d42384f60d07b28d6b27084314c8e38f8b89adfe4fce7d67333b3e6b186d6dd9",
                "76378ac2f8d33d34966da32d666aac644877a1c95805d14f119fc3ab191ff6ec",
                "12dea9cba50acc5256b3767e97de96603f0e5ecdaffe35ba6a9e1dc74863663f",
                "6f2ba135fac2fafbe7ad67563f3f1d634f83eac57139cb0fafbd7ea17cc133b4",
                "f0b0c0db65f39ca517610f57365d7dab46307fb89ee17cf32747c7d57f6ba900",
                "45016d1d738824bb93052d1aae19d0903c0b23326f9755f0ff0ee5262b904f48",
                "dbc735d5c97553037411b54dc362e582bf7ee39ff789d9840321ce2bb3c2b188",
                "07c0fea1a5a9a8ad466dc669100df1ed191a743cc7c9162aaf45b688d2118d67",
                "554c126ed645f8e9023e069ce6ca809564b2386cf5b32384ef9c5f05f590dab2",
                "3db0b9b2b2b93273390a8ad93228c1ea441db0d04af79c3ca4ff579655d6df22",
                "e5ab59951a4a6ee0901277623920c4a956c180bb135d0e930a3c1b3b6823cd57",
                "16d5307e1d01d7c7e33ef1dcb2dc2535b11f8fadf5d1b4cbb8262dc3b1a1f2b2",
                "5f3d50cf590cc29b6c7c010aac06adc6f1fe9bfe0b2a19419efefb9125373638",
                "b3db1f2c17d4d70d4fde97999cf3b6b5e9cedde211daa02b2b3ad55c61885746",
                "beaee8f3f4afffa3dbff73ecc33ca0a70ae88c9a9cd2c395b572a22304af2351",
                "87fc083f786fce164cf23cd9fd6141ee390d91c4c75ffcad874fd6ae29802059",
                "c70ede158b2143deef144757a6ff537698567c91c752b5781adaaa2746b0de4c",
                "66c6884b823079b9549603fb11b474c0c9a1065f6b7214bafd96623ef28a9a03"
            ],
            "type": "XHR",
            "firstPartyCookies": {},
            "firstPartyCookiesSent": {},
            "exampleSites": [
                "m.tnaflix.com",
                "www.pornorama.com",
                "bokep.uno",
                "ge.xhamster.com",
                "www.xhammer.net",
                "sexdollporn.com",
                "bokepjepang.org",
                "massagepornx.com",
                "www.xnxx20.com",
                "br.spankbang.com",
                "morigin.tnaflix.com",
                "phimxsex.com",
                "xxxx2024.com",
                "en.pornohd.porn",
                "www.tnaflix.com",
                "bokepindopro.com",
                "pornobrasil.com",
                "ciciindo.com",
                "trendpornvids.com",
                "www.madurashd.com"
            ]
        },
        {
            "rule": "livejasmin\\.com\\/",
            "cookies": 0,
            "fingerprinting": 0,
            "subdomains": [
                "vast"
            ],
            "apis": {},
            "sites": 5,
            "prevalence": 0.0000354,
            "cnames": [],
            "responseHashes": [
                "6c5f882edf7e83c997547a4ff5b705534a55608ba2c97b7987e2f84b34153a3e",
                "5f5635e6b3d9d8cd77a21a12eb803a81252d30c0858ed080232c1c65530fbe32",
                "2a52917fcc4138401ac5646db2bd2ce711acc784a5f28b132b5645f2e2a18a3a",
                "3886df0422f47fa0a6ef4ce80225769866d81c0332c76904d3ef27b0ad03d0ba"
            ],
            "type": "Fetch",
            "firstPartyCookies": {},
            "firstPartyCookiesSent": {},
            "exampleSites": [
                "letsjerk.tv",
                "wporncomics.com",
                "www.analdin.com",
                "www.pornhits.com",
                "www.trendyporn.com"
            ]
        },
        {
            "rule": "livejasmin\\.com\\/ccs\\.php",
            "cookies": 0.0000141,
            "fingerprinting": 0,
            "subdomains": [
                "ccs"
            ],
            "apis": {},
            "sites": 2,
            "prevalence": 0.0000141,
            "cnames": [],
            "responseHashes": [],
            "type": "Image",
            "firstPartyCookies": {},
            "firstPartyCookiesSent": {},
            "exampleSites": [
                "letsjerk.tv",
                "www.analdin.com"
            ]
        },
        {
            "rule": "livejasmin\\.com\\/post\\/exralifk\\/vip",
            "cookies": 0,
            "fingerprinting": 0,
            "subdomains": [
                "crmapt"
            ],
            "apis": {},
            "sites": 3,
            "prevalence": 0.0000212,
            "cnames": [],
            "responseHashes": [
                "62d5a9908c119465bc5eb6032acf383527bfa57846600a56e10868274bba3b7f"
            ],
            "type": "Document",
            "firstPartyCookies": {},
            "firstPartyCookiesSent": {},
            "exampleSites": [
                "manhwahentai.me",
                "www.tumbex.com",
                "zeusporn.com"
            ]
        },
        {
            "rule": "livejasmin\\.com\\/si\\/prls\\/",
            "cookies": 0,
            "fingerprinting": 0,
            "subdomains": [
                "crmapt"
            ],
            "apis": {},
            "sites": 3,
            "prevalence": 0.0000212,
            "cnames": [],
            "responseHashes": [
                "7ec8ca5461cda2069f45f2a6a050fd0b59512b6f522f8165f3f2cf771cd14300",
                "d929dc81d402208a5e63571a54e0ead91d61927f83644a11423d482309c898a7"
            ],
            "type": "Document",
            "firstPartyCookies": {},
            "firstPartyCookiesSent": {},
            "exampleSites": [
                "vintage-erotica-forum.com",
                "www.planetsuzy.org",
                "www.sleazyneasy.com"
            ]
        },
        {
            "rule": "livejasmin\\.com\\/discount\\/hh90\\/",
            "cookies": 0,
            "fingerprinting": 0,
            "subdomains": [
                "crmapt"
            ],
            "apis": {},
            "sites": 2,
            "prevalence": 0.0000141,
            "cnames": [],
            "responseHashes": [
                "26d262d965ed487481b14bba63808fe80e37d58d3fe2c428d9c90ade158bebb7"
            ],
            "type": "Document",
            "firstPartyCookies": {},
            "firstPartyCookiesSent": {},
            "exampleSites": [
                "sexwebvideo.net",
                "www.sexwebvideo.net"
            ]
        }
    ],
    "categories": [],
    "performance": {},
    "cookies": 0.0000141,
    "topInitiators": [
        {
            "domain": "xvideos-cdn.com",
            "prevalence": 0.2909090909090909
        },
        {
            "domain": "first party",
            "prevalence": 0.23636363636363636
        },
        {
            "domain": "maredpt.com",
            "prevalence": 0.10909090909090909
        },
        {
            "domain": "addin1.name",
            "prevalence": 0.10909090909090909
        },
        {
            "domain": "awecre.com",
            "prevalence": 0.09090909090909091
        },
        {
            "domain": "tsyndicate.com",
            "prevalence": 0.03636363636363636
        },
        {
            "domain": "wmcdct.com",
            "prevalence": 0.03636363636363636
        },
        {
            "domain": "sb-cd.com",
            "prevalence": 0.01818181818181818
        },
        {
            "domain": "xhcdn.com",
            "prevalence": 0.01818181818181818
        },
        {
            "domain": "tapioni.com",
            "prevalence": 0.01818181818181818
        }
    ],
    "types": {
        "XHR": 25,
        "Fetch": 5,
        "Image": 2,
        "Document": 8
    },
    "nameservers": [
        "ns2.dditservices.com",
        "ns1.dditservices.com"
    ]
}