{
    "domain": "tncid.app",
    "owner": {},
    "source": [
        "DuckDuckGo-US"
    ],
    "prevalence": 0.000141,
    "sites": 20,
    "subdomains": [
        "js",
        "im"
    ],
    "cnames": [],
    "fingerprinting": 3,
    "resources": [
        {
            "rule": "tncid\\.app\\/route\\.js",
            "cookies": 0.0000637,
            "fingerprinting": 3,
            "subdomains": [
                "js"
            ],
            "apis": {
                "Navigator.prototype.userAgent": 9,
                "NavigatorUAData.prototype.brands": 9,
                "Date.prototype.getTime": 9,
                "Document.cookie getter": 9,
                "window.localStorage": 9,
                "Document.cookie setter": 9,
                "Navigator.prototype.vendor": 8,
                "OfflineAudioContext.prototype.constructor": 8,
                "Navigator.prototype.productSub": 8,
                "CanvasRenderingContext2D.prototype.isPointInPath": 8,
                "Navigator.prototype.doNotTrack": 8,
                "Screen.prototype.orientation": 8,
                "Navigator.prototype.platform": 8,
                "Navigator.prototype.maxTouchPoints": 8,
                "Navigator.prototype.plugins": 8,
                "window.devicePixelRatio": 8,
                "HTMLCanvasElement.prototype.toDataURL": 8,
                "WebGLRenderingContext.prototype.getSupportedExtensions": 8,
                "WebGLRenderingContext.prototype.getParameter": 8,
                "WebGLRenderingContext.prototype.getContextAttributes": 8,
                "WebGLRenderingContext.prototype.getExtension": 8,
                "WebGLRenderingContext.prototype.getShaderPrecisionFormat": 8,
                "AudioBuffer.prototype.getChannelData": 8,
                "Navigator.prototype.language": 8,
                "Navigator.prototype.languages": 8,
                "Screen.prototype.width": 8,
                "Screen.prototype.height": 8,
                "Screen.prototype.availHeight": 8,
                "Screen.prototype.availWidth": 8,
                "Intl.DateTimeFormat.prototype.resolvedOptions": 8,
                "Navigator.prototype.appCodeName": 8,
                "Navigator.prototype.appName": 8,
                "Navigator.prototype.appVersion": 8,
                "Navigator.prototype.cookieEnabled": 8,
                "Navigator.prototype.onLine": 8,
                "Navigator.prototype.javaEnabled": 6,
                "Screen.prototype.colorDepth": 8,
                "Navigator.prototype.deviceMemory": 8,
                "Navigator.prototype.hardwareConcurrency": 8,
                "Date.prototype.getTimezoneOffset": 8,
                "Navigator.prototype.webdriver": 8
            },
            "sites": 9,
            "prevalence": 0.0000637,
            "cnames": [],
            "responseHashes": [
                "1b30fc1cebce74ae2beb09f76e02e7f3912aeaef5572f7f0588f5e0c92a32095"
            ],
            "type": "Script",
            "firstPartyCookies": {
                "tncid": {
                    "ttl": 31536014,
                    "length": 36,
                    "prevalence": 0.00004951335445903124,
                    "uniqueness": 0.2857142857142857
                },
                "cacheid": {
                    "ttl": 31536014,
                    "length": 31,
                    "prevalence": 0.00005658669081032141,
                    "uniqueness": 1
                }
            },
            "firstPartyCookiesSent": {},
            "exampleSites": [
                "corriere.it",
                "milano.corriere.it",
                "movieplayer.it",
                "multiplayer.it",
                "roma.corriere.it",
                "www.corriere.it",
                "www.gazzetta.it",
                "www.giroditalia.it",
                "www.notizie.it"
            ]
        },
        {
            "rule": "tncid\\.app\\/cacheid",
            "cookies": 0,
            "fingerprinting": 0,
            "subdomains": [
                "js"
            ],
            "apis": {},
            "sites": 17,
            "prevalence": 0.00012,
            "cnames": [],
            "responseHashes": [
                "cbd100d7cdab80ff21d2b11415e4d289beb2560bf07960915286afbeb5460c12"
            ],
            "type": "Fetch",
            "firstPartyCookies": {},
            "firstPartyCookiesSent": {},
            "exampleSites": [
                "corriere.it",
                "forums.bluemoon-mcfc.co.uk",
                "milano.corriere.it",
                "movieplayer.it",
                "multiplayer.it",
                "roma.corriere.it",
                "salarysport.com",
                "tv24.co.uk",
                "tvguide.co.uk",
                "www.corriere.it",
                "www.gazzetta.it",
                "www.giroditalia.it",
                "www.notizie.it",
                "www.planetfootball.com",
                "www.teamtalk.com",
                "www.tuttogreen.it",
                "www.wheresthematch.com"
            ]
        },
        {
            "rule": "tncid\\.app\\/d29c2605-2cfa-43b3-a237-5dfdaf10a077\\/config\\.js",
            "cookies": 0,
            "fingerprinting": 0,
            "subdomains": [
                "js"
            ],
            "apis": {},
            "sites": 4,
            "prevalence": 0.0000283,
            "cnames": [],
            "responseHashes": [
                "64252fdc2bbc849bb8cedb482b8b3fb818c393a4702dd86484ddd78b30aa6502"
            ],
            "type": "Fetch",
            "firstPartyCookies": {},
            "firstPartyCookiesSent": {},
            "exampleSites": [
                "corriere.it",
                "milano.corriere.it",
                "roma.corriere.it",
                "www.corriere.it"
            ]
        },
        {
            "rule": "tncid\\.app\\/bd\\/pv",
            "cookies": 0,
            "fingerprinting": 0,
            "subdomains": [
                "js"
            ],
            "apis": {},
            "sites": 13,
            "prevalence": 0.000092,
            "cnames": [],
            "responseHashes": [],
            "type": "Preflight",
            "firstPartyCookies": {},
            "firstPartyCookiesSent": {},
            "exampleSites": [
                "corriere.it",
                "forums.bluemoon-mcfc.co.uk",
                "milano.corriere.it",
                "movieplayer.it",
                "multiplayer.it",
                "roma.corriere.it",
                "tv24.co.uk",
                "tvguide.co.uk",
                "www.corriere.it",
                "www.gazzetta.it",
                "www.giroditalia.it",
                "www.tuttogreen.it",
                "www.wheresthematch.com"
            ]
        },
        {
            "rule": "tncid\\.app\\/bd\\/pv",
            "cookies": 0.000092,
            "fingerprinting": 0,
            "subdomains": [
                "js"
            ],
            "apis": {},
            "sites": 13,
            "prevalence": 0.000092,
            "cnames": [],
            "responseHashes": [
                "4ef3d37a59a33531de0bf7e0f33f8856c0b5c4927af1218803205db0b139d699",
                "486e32ad9cfa34c26c5c22252cf7b31f137b39f261a4c36d72730731755937da",
                "45877593073d9e38d1dfd660a0af88939ef1d385043fe15a497a8567f46125f7",
                "73d5dd695746a81791a25d513fb8c6230a92a164b4d0ce06189e28cfffb64475",
                "c2f6640d8b0783957d93d2b480d6d398f75281c15fba3f1eaf2d8e2303218555",
                "626e6e1bfcfb3c265269e1e2d9bb1219be6d10c88bbb9a269a2927e96a3d335e",
                "2a672ab8396405eddd16b90c3b5a25710f60a3b248267593d9edb89d06d5d310",
                "7ca65ee38c4d543106bacf8b99f181c1797421a79dc9535e1655a742e68681cd"
            ],
            "type": "Fetch",
            "firstPartyCookies": {},
            "firstPartyCookiesSent": {},
            "exampleSites": [
                "corriere.it",
                "forums.bluemoon-mcfc.co.uk",
                "milano.corriere.it",
                "movieplayer.it",
                "multiplayer.it",
                "roma.corriere.it",
                "tv24.co.uk",
                "tvguide.co.uk",
                "www.corriere.it",
                "www.gazzetta.it",
                "www.giroditalia.it",
                "www.tuttogreen.it",
                "www.wheresthematch.com"
            ]
        },
        {
            "rule": "tncid\\.app\\/im\\/ppid-collect",
            "cookies": 0,
            "fingerprinting": 0,
            "subdomains": [
                "js"
            ],
            "apis": {},
            "sites": 11,
            "prevalence": 0.0000778,
            "cnames": [],
            "responseHashes": [
                "d346801abbf9bb4e9e9a055239053d4ab5596514304f601a6c70604187acb744"
            ],
            "type": "Fetch",
            "firstPartyCookies": {},
            "firstPartyCookiesSent": {
                "tncid": 0.00005658669081032141
            },
            "exampleSites": [
                "corriere.it",
                "forums.bluemoon-mcfc.co.uk",
                "milano.corriere.it",
                "movieplayer.it",
                "multiplayer.it",
                "tv24.co.uk",
                "tvguide.co.uk",
                "www.corriere.it",
                "www.gazzetta.it",
                "www.tuttogreen.it",
                "www.wheresthematch.com"
            ]
        },
        {
            "rule": "tncid\\.app\\/gif",
            "cookies": 0,
            "fingerprinting": 0,
            "subdomains": [
                "im"
            ],
            "apis": {},
            "sites": 9,
            "prevalence": 0.0000637,
            "cnames": [],
            "responseHashes": [],
            "type": "Fetch",
            "firstPartyCookies": {},
            "firstPartyCookiesSent": {
                "tncid": 0.00004951335445903124
            },
            "exampleSites": [
                "corriere.it",
                "forums.bluemoon-mcfc.co.uk",
                "milano.corriere.it",
                "movieplayer.it",
                "multiplayer.it",
                "tv24.co.uk",
                "www.gazzetta.it",
                "www.tuttogreen.it",
                "www.wheresthematch.com"
            ]
        },
        {
            "rule": "tncid\\.app\\/remote\\.min\\.js",
            "cookies": 0.0000283,
            "fingerprinting": 3,
            "subdomains": [
                "js"
            ],
            "apis": {
                "Navigator.prototype.userAgent": 4,
                "NavigatorUAData.prototype.brands": 4,
                "Date.prototype.getTime": 4,
                "Document.cookie getter": 4,
                "window.localStorage": 4,
                "Document.cookie setter": 4,
                "Navigator.prototype.vendor": 2,
                "OfflineAudioContext.prototype.constructor": 1,
                "Navigator.prototype.productSub": 2,
                "CanvasRenderingContext2D.prototype.isPointInPath": 1,
                "Navigator.prototype.doNotTrack": 2,
                "Screen.prototype.orientation": 2,
                "Navigator.prototype.platform": 2,
                "Navigator.prototype.maxTouchPoints": 2,
                "Navigator.prototype.plugins": 2,
                "window.devicePixelRatio": 2,
                "HTMLCanvasElement.prototype.toDataURL": 1,
                "WebGLRenderingContext.prototype.getSupportedExtensions": 1,
                "WebGLRenderingContext.prototype.getParameter": 1,
                "WebGLRenderingContext.prototype.getContextAttributes": 1,
                "WebGLRenderingContext.prototype.getExtension": 1,
                "WebGLRenderingContext.prototype.getShaderPrecisionFormat": 1,
                "AudioBuffer.prototype.getChannelData": 2,
                "Navigator.prototype.language": 2,
                "Navigator.prototype.languages": 2,
                "Screen.prototype.width": 2,
                "Screen.prototype.height": 2,
                "Screen.prototype.availHeight": 2,
                "Screen.prototype.availWidth": 2,
                "Intl.DateTimeFormat.prototype.resolvedOptions": 2,
                "Navigator.prototype.appCodeName": 2,
                "Navigator.prototype.appName": 2,
                "Navigator.prototype.appVersion": 2,
                "Navigator.prototype.cookieEnabled": 2,
                "Navigator.prototype.onLine": 2,
                "Navigator.prototype.javaEnabled": 1,
                "Screen.prototype.colorDepth": 2,
                "Navigator.prototype.deviceMemory": 1,
                "Navigator.prototype.hardwareConcurrency": 2,
                "Date.prototype.getTimezoneOffset": 2,
                "Navigator.prototype.webdriver": 1
            },
            "sites": 8,
            "prevalence": 0.0000566,
            "cnames": [],
            "responseHashes": [
                "1b30fc1cebce74ae2beb09f76e02e7f3912aeaef5572f7f0588f5e0c92a32095"
            ],
            "type": "Script",
            "firstPartyCookies": {
                "tncid": {
                    "ttl": 31536023,
                    "length": 36,
                    "prevalence": 0.0000070733363512901765,
                    "uniqueness": 1
                },
                "cacheid": {
                    "ttl": 31536022,
                    "length": 31,
                    "prevalence": 0.000014146672702580353,
                    "uniqueness": 1
                }
            },
            "firstPartyCookiesSent": {},
            "exampleSites": [
                "bluemoon-mcfc.co.uk",
                "salarysport.com",
                "tv24.co.uk",
                "tvguide.co.uk",
                "www.planetfootball.com",
                "www.teamtalk.com",
                "www.tuttogreen.it",
                "www.wheresthematch.com"
            ]
        },
        {
            "rule": "tncid\\.app\\/78b8a63f-adb5-4221-b3d7-fbf255fde0d0\\/config\\.js",
            "cookies": 0,
            "fingerprinting": 0,
            "subdomains": [
                "js"
            ],
            "apis": {},
            "sites": 8,
            "prevalence": 0.0000566,
            "cnames": [],
            "responseHashes": [
                "052597e70056f153bf11008617079e78c46c94d8707fdb4a0755e28ca5672bf0"
            ],
            "type": "Fetch",
            "firstPartyCookies": {},
            "firstPartyCookiesSent": {},
            "exampleSites": [
                "bluemoon-mcfc.co.uk",
                "salarysport.com",
                "tv24.co.uk",
                "tvguide.co.uk",
                "www.planetfootball.com",
                "www.teamtalk.com",
                "www.tuttogreen.it",
                "www.wheresthematch.com"
            ]
        },
        {
            "rule": "tncid\\.app\\/im\\/gif",
            "cookies": 0,
            "fingerprinting": 0,
            "subdomains": [
                "js"
            ],
            "apis": {},
            "sites": 7,
            "prevalence": 0.0000495,
            "cnames": [],
            "responseHashes": [
                "d346801abbf9bb4e9e9a055239053d4ab5596514304f601a6c70604187acb744"
            ],
            "type": "Fetch",
            "firstPartyCookies": {},
            "firstPartyCookiesSent": {
                "tncid": 0.000028293345405160706
            },
            "exampleSites": [
                "bluemoon-mcfc.co.uk",
                "movieplayer.it",
                "multiplayer.it",
                "tv24.co.uk",
                "tvguide.co.uk",
                "www.tuttogreen.it",
                "www.wheresthematch.com"
            ]
        },
        {
            "rule": "tncid\\.app\\/bcbf0cf9-29b5-4015-8110-776a06298439\\/config\\.js",
            "cookies": 0,
            "fingerprinting": 0,
            "subdomains": [
                "js"
            ],
            "apis": {},
            "sites": 2,
            "prevalence": 0.0000141,
            "cnames": [],
            "responseHashes": [
                "09e45303b1fe00293cc9e2c74a4fe456275ea502c1537760d90de998196f0526"
            ],
            "type": "Fetch",
            "firstPartyCookies": {},
            "firstPartyCookiesSent": {},
            "exampleSites": [
                "movieplayer.it",
                "multiplayer.it"
            ]
        },
        {
            "rule": "tncid\\.app\\/7e6d99e6-51ab-4a6e-a4d5-c5ecad5601fb\\/config\\.js",
            "cookies": 0,
            "fingerprinting": 0,
            "subdomains": [
                "js"
            ],
            "apis": {},
            "sites": 3,
            "prevalence": 0.0000212,
            "cnames": [],
            "responseHashes": [
                "64252fdc2bbc849bb8cedb482b8b3fb818c393a4702dd86484ddd78b30aa6502"
            ],
            "type": "Fetch",
            "firstPartyCookies": {},
            "firstPartyCookiesSent": {},
            "exampleSites": [
                "gazzetta.it",
                "www.gazzetta.it",
                "www.giroditalia.it"
            ]
        }
    ],
    "categories": [],
    "performance": {},
    "cookies": 0.000127,
    "topInitiators": [
        {
            "domain": "4strokemedia.com",
            "prevalence": 0.45
        },
        {
            "domain": "corriereobjects.it",
            "prevalence": 0.25
        },
        {
            "domain": "clickiocmp.com",
            "prevalence": 0.1
        },
        {
            "domain": "gazzettaobjects.it",
            "prevalence": 0.1
        },
        {
            "domain": "rcsobjects.it",
            "prevalence": 0.05
        },
        {
            "domain": "googletagmanager.com",
            "prevalence": 0.05
        }
    ],
    "types": {
        "Script": 17,
        "Fetch": 74,
        "Preflight": 13
    },
    "nameservers": [
        "ns-cloud-c1.googledomains.com",
        "ns-cloud-c3.googledomains.com",
        "ns-cloud-c2.googledomains.com",
        "ns-cloud-c4.googledomains.com"
    ]
}